unstructured_expanded/__init__.py
unstructured_expanded/tools.py
unstructured_expanded/partition/__init__.py
unstructured_expanded/partition/docx/__init__.py
unstructured_expanded/partition/docx/partition_docx.py
unstructured_expanded/partition/docx/partition_picture.py
unstructured_expanded/partition/pdf/__init__.py
unstructured_expanded/partition/pdf/partition_pdf.py
unstructured_expanded/partition/pptx/__init__.py
unstructured_expanded/partition/pptx/partition_picture.py
unstructured_expanded/partition/pptx/partition_pptx.py
unstructured_expanded-0.17.2.dist-info/licenses/LICENSE
unstructured_expanded-0.17.2.dist-info/METADATA
unstructured_expanded-0.17.2.dist-info/WHEEL
unstructured_expanded-0.17.2.dist-info/top_level.txt
unstructured_expanded-0.17.2.dist-info/RECORD
