Metadata-Version: 2.4
Name: unstructured_expanded
Version: 0.17.2
Summary: Expansion to the unstructured package, adding support for image extraction.
Home-page: https://github.com/isaackogan/unstructured_expanded
Author: Isaac Kogan
Author-email: info@isaackogan.com
License: MIT
Keywords: nlp,natural language processing,text,documents,images,image extraction,pdf,docx,pptx,semantic,semantic analysis,semantic parsing,semantic extraction,unstructured
Classifier: Development Status :: 4 - Beta
Classifier: Intended Audience :: Developers
Classifier: Topic :: Software Development :: Build Tools
Classifier: License :: OSI Approved :: MIT License
Classifier: Natural Language :: English
Classifier: Programming Language :: Python :: 3.8
Classifier: Programming Language :: Python :: 3.9
Classifier: Programming Language :: Python :: 3.10
Classifier: Programming Language :: Python :: 3.11
License-File: LICENSE
Requires-Dist: unstructured==0.17.2
Dynamic: author
Dynamic: author-email
Dynamic: classifier
Dynamic: description
Dynamic: description-content-type
Dynamic: home-page
Dynamic: keywords
Dynamic: license
Dynamic: license-file
Dynamic: requires-dist
Dynamic: summary
